autopetroleum/__init__.py
autopetroleum/correlation.py
autopetroleum/evaluate.py
autopetroleum/plot.py
autopetroleum/design/__init__.py
autopetroleum/design/datapreprocess.py
autopetroleum/design/main.py
autopetroleum/design/opt.py
autopetroleum/design/production.py
autopetroleum-0.0.1.dist-info/LICENSE
autopetroleum-0.0.1.dist-info/METADATA
autopetroleum-0.0.1.dist-info/WHEEL
autopetroleum-0.0.1.dist-info/top_level.txt
autopetroleum-0.0.1.dist-info/RECORD
